vc_filter/.DS_Store
vc_filter/__init__.py
vc_filter/src/.DS_Store
vc_filter/src/apply.py
vc_filter/src/others.py
vc_filter-1.1.20.dist-info/METADATA
vc_filter-1.1.20.dist-info/WHEEL
vc_filter-1.1.20.dist-info/RECORD
