Metadata-Version: 2.1
Name: vc-filter
Version: 1.1.20
Summary: VC-filter is a new high-quality edge detector based on the Visual Cortex study
License: MIT
Author: Boris Kravtsov
Author-email: kravtsov.development@gmail.com
Requires-Python: >=3.10,<4.0
Classifier: License :: OSI Approved :: MIT License
Classifier: Programming Language :: Python :: 3
Classifier: Programming Language :: Python :: 3.10
Classifier: Programming Language :: Python :: 3.11
Requires-Dist: opencv-python-headless (>=4.8.0.74,<5.0.0.0)
